django_utils_kit/__init__.py
django_utils_kit/admin.py
django_utils_kit/emails.py
django_utils_kit/exceptions.py
django_utils_kit/files.py
django_utils_kit/images.py
django_utils_kit/models.py
django_utils_kit/network.py
django_utils_kit/permissions.py
django_utils_kit/serializers.py
django_utils_kit/test_runners.py
django_utils_kit/test_utils.py
django_utils_kit/viewsets.py
django_utils_kit-1.0.2.dist-info/licenses/LICENSE
django_utils_kit-1.0.2.dist-info/METADATA
django_utils_kit-1.0.2.dist-info/WHEEL
django_utils_kit-1.0.2.dist-info/top_level.txt
django_utils_kit-1.0.2.dist-info/RECORD
