Metadata-Version: 2.4
Name: django_utils_kit
Version: 1.0.2
Summary: Bundle of useful classes and functions for Django
Author-email: Jordan Kowal <kowaljordan@gmail.com>
Maintainer-email: Jordan Kowal <kowaljordan@gmail.com>
License: MIT License
Project-URL: Changelog, https://github.com/Jordan-Kowal/django-utils-kit/blob/main/CHANGELOG.md
Project-URL: Issues, https://github.com/Jordan-Kowal/django-utils-kit/issues
Project-URL: Release notes, https://github.com/Jordan-Kowal/django-utils-kit/releases
Project-URL: Source, https://github.com/Jordan-Kowal/django-utils-kit
Keywords: django,utils,utilities,kit,djangorestframework,drf
Classifier: Development Status :: 5 - Production/Stable
Classifier: Intended Audience :: Developers
Classifier: License :: OSI Approved :: MIT License
Classifier: Operating System :: Microsoft :: Windows
Classifier: Operating System :: POSIX
Classifier: Operating System :: Unix
Classifier: Operating System :: MacOS
Classifier: Programming Language :: Python
Classifier: Programming Language :: Python :: 3
Classifier: Programming Language :: Python :: 3.9
Classifier: Programming Language :: Python :: 3.10
Classifier: Programming Language :: Python :: 3.11
Classifier: Programming Language :: Python :: 3.12
Classifier: Programming Language :: Python :: 3.13
Classifier: Programming Language :: Python :: Implementation :: CPython
Classifier: Topic :: Software Development
Requires-Python: >=3.9
License-File: LICENSE
Requires-Dist: django>=4.0.0
Requires-Dist: djangorestframework>=3.13.0
Requires-Dist: pillow>=11.0.0
Dynamic: license-file
